agentmind/__init__.py
agentmind/decorators.py
agentmind/api/__init__.py
agentmind/api/client.py
agentmind/core/__init__.py
agentmind/core/memory.py
agentmind/core/types.py
agentmind/integrations/__init__.py
agentmind/integrations/langchain.py
agentmind/integrations/openai.py
agentmind-0.3.5.dist-info/licenses/LICENSE
tests/__init__.py
tests/test_api_only.py
tests/test_billing.py
tests/test_full_system.py
tests/test_integration.py
tests/test_memory.py
tests/test_openai_integration.py
agentmind-0.3.5.dist-info/METADATA
agentmind-0.3.5.dist-info/WHEEL
agentmind-0.3.5.dist-info/top_level.txt
agentmind-0.3.5.dist-info/RECORD
