Metadata-Version: 2.4
Name: agentmind
Version: 0.3.5
Summary: Plug-and-play memory for AI agents. Simple, fast, and powerful.
Home-page: https://github.com/muiez/agentmind
Author: muiez
Author-email: 
Maintainer: muiez
License: MIT
Project-URL: Homepage, https://github.com/muiez/agentmind
Project-URL: Repository, https://github.com/muiez/agentmind
Project-URL: Issues, https://github.com/muiez/agentmind/issues
Classifier: Development Status :: 3 - Alpha
Classifier: Intended Audience :: Developers
Classifier: Topic :: Scientific/Engineering :: Artificial Intelligence
Classifier: License :: OSI Approved :: MIT License
Classifier: Programming Language :: Python :: 3
Classifier: Programming Language :: Python :: 3.9
Classifier: Programming Language :: Python :: 3.10
Classifier: Programming Language :: Python :: 3.11
Requires-Python: >=3.9
License-File: LICENSE
Requires-Dist: requests>=2.28.0
Requires-Dist: pydantic>=2.0.0
Requires-Dist: numpy>=1.24.0
Requires-Dist: tiktoken>=0.5.0
Requires-Dist: python-dateutil>=2.8.0
Requires-Dist: openai<2.0.0,>=1.107.1
Provides-Extra: dev
Requires-Dist: pytest>=7.0.0; extra == "dev"
Requires-Dist: pytest-asyncio>=0.21.0; extra == "dev"
Requires-Dist: black>=23.0.0; extra == "dev"
Requires-Dist: flake8>=6.0.0; extra == "dev"
Requires-Dist: mypy>=1.0.0; extra == "dev"
Requires-Dist: pytest-cov>=4.0.0; extra == "dev"
Provides-Extra: langchain
Requires-Dist: langchain>=0.1.0; extra == "langchain"
Provides-Extra: openai
Requires-Dist: openai>=1.0.0; extra == "openai"
Dynamic: home-page
Dynamic: license-file
Dynamic: requires-python
